brdm/BaseRefData.py
brdm/NcbiBlastData.py
brdm/NcbiData.py
brdm/RefDataInterface.py
brdm/__init__.py
brdm/brdm_root.py
brdm/config.yaml.sample
brdm-0.1.7.data/scripts/main.py
brdm-0.1.7.dist-info/METADATA
brdm-0.1.7.dist-info/RECORD
brdm-0.1.7.dist-info/WHEEL
brdm-0.1.7.dist-info/entry_points.txt
brdm-0.1.7.dist-info/top_level.txt
