Metadata-Version: 2.1
Name: brdm
Version: 0.1.7
Summary: Bioinformatics Reference Data Manager is an application used to download, backup and update of     reference data, required for various bioinformatics analysis
Home-page: https://github.com/AAFC-BICoE/reference-data-manager
Author: Oksana Korol
Author-email: oksana.korol@agr.gc.ca
License: UNKNOWN
Platform: UNKNOWN
Classifier: Programming Language :: Python :: 3
Classifier: License :: OSI Approved :: MIT License
Requires-Dist: PyYAML
Requires-Dist: requests
